cryptoauthlib/tng.py
cryptoauthlib/libcryptoauth.SOVERSION.dylib
cryptoauthlib/library.py
cryptoauthlib/device.py
cryptoauthlib/libcryptoauth.dylib
cryptoauthlib/iface.py
cryptoauthlib/atjwt.py
cryptoauthlib/__init__.py
cryptoauthlib/atcab.py
cryptoauthlib/atcacert.py
cryptoauthlib/sha206_api.py
cryptoauthlib/exceptions.py
cryptoauthlib/atcaenum.py
cryptoauthlib/status.py
cryptoauthlib/cryptoauth.json
cryptoauthlib-20250916.dist-info/RECORD
cryptoauthlib-20250916.dist-info/WHEEL
cryptoauthlib-20250916.dist-info/top_level.txt
cryptoauthlib-20250916.dist-info/METADATA
cryptoauthlib-20250916.dist-info/licenses/LICENSE.txt
