Metadata-Version: 2.4
Name: cryptoauthlib
Version: 20250916
Summary: Python Wrapper Library for Microchip Security Products
Home-page: https://github.com/MicrochipTech/cryptoauthlib
Download-URL: https://github.com/MicrochipTech/cryptoauthlib/archive/.tar.gz
Author: Microchip Technology Inc
Author-email: support@microchip.com
License: Other
Project-URL: Documentation, https://github.com/MicrochipTech/cryptoauthlib/wiki/python
Project-URL: Source, https://github.com/MicrochipTech/cryptoauthlib
Project-URL: Tracker, https://github.com/MicrochipTech/cryptoauthlib/issues
Keywords: Microchip ATECC508A ATECC608 ECDSA ECDH
Classifier: Development Status :: 4 - Beta
Classifier: License :: Other/Proprietary License
Classifier: Intended Audience :: Developers
Classifier: Programming Language :: Python
Classifier: Programming Language :: Python :: 2
Classifier: Programming Language :: Python :: 2.7
Classifier: Programming Language :: Python :: 3
Classifier: Operating System :: OS Independent
Requires-Python: >=3.8.0
License-File: LICENSE.txt
Requires-Dist: enum34; python_version < "3.4"
Dynamic: author
Dynamic: author-email
Dynamic: classifier
Dynamic: description
Dynamic: description-content-type
Dynamic: download-url
Dynamic: home-page
Dynamic: keywords
Dynamic: license
Dynamic: license-file
Dynamic: project-url
Dynamic: requires-dist
Dynamic: requires-python
Dynamic: summary
